lienv-0.5.0.dist-info/METADATA
lienv-0.5.0.dist-info/WHEEL
lienv-0.5.0.dist-info/license_files/LICENSE
lienv/__init__.py
lienv/__init__.pyi
lienv/py.typed
lienv/lienv.cpython-38-darwin.so
lienv-0.5.0.dist-info/RECORD
