Metadata-Version: 2.1
Name: lienv
Version: 0.5.0
Classifier: Programming Language :: Rust
Classifier: Programming Language :: Python :: 3.8
Classifier: Programming Language :: Python :: 3.9
Classifier: Programming Language :: Python :: 3.10
Classifier: Programming Language :: Python :: 3.11
Classifier: Programming Language :: Python :: Implementation :: CPython
Classifier: Programming Language :: Python :: Implementation :: PyPy
License-File: LICENSE
Summary: A tool to easily get typed values out of strings stored in environment variables.
Keywords: environment,variables,types,parsing,rust
Author: Liander Medeiros
Author-email: liander.medeiros@gmail.com
Requires-Python: >=3.8
Project-URL: homepage, https://github.com/liander-medeiros/lienv-py
Project-URL: documentation, https://github.com/liander-medeiros/lienv-py/blob/master/README.md
Project-URL: repository, https://github.com/liander-medeiros/lienv-py
Project-URL: changelog, https://github.com/liander-medeiros/lienv-py/blob/master/CHANGELOG.md
